usagov/__init__.py
usagov/__version__.py
usagov/congress/__init__.py
usagov/congress/client.py
usagov/congress/exceptions.py
usagov/congress/services/__init__.py
usagov/congress/services/amendment.py
usagov/congress/services/bill.py
usagov/congress/services/committee.py
usagov/congress/services/communication.py
usagov/congress/services/congress.py
usagov/congress/services/hearing.py
usagov/congress/services/law.py
usagov/congress/services/member.py
usagov/congress/services/nomination.py
usagov/congress/services/record.py
usagov/congress/services/summary.py
usagov/congress/services/treaty.py
usagov/congress/utils/__init__.py
usagov/congress/utils/utils.py
usagov/congress/utils/utils.pyi
usagov-0.1.0.dist-info/LICENSE
usagov-0.1.0.dist-info/METADATA
usagov-0.1.0.dist-info/WHEEL
usagov-0.1.0.dist-info/RECORD
